{"cameraMode":{"drawMode":0,"name":"Shaded","section":"Shading Mode"},"sceneLighting":true,"audioPlay":false,"sceneViewState":{"m_AlwaysRefresh":false,"showFog":true,"showSkybox":false,"showFlares":true,"showImageEffects":true,"showParticleSystems":true,"showVisualEffectGraphs":true,"m_FxEnabled":true},"in2DMode":false,"pivot":{"x":-17.18187713623047,"y":-22.524574279785158,"z":61.50384521484375},"rotation":{"x":-0.2526259124279022,"y":0.24184978008270265,"z":-0.06536877155303955,"w":-0.934581458568573},"size":47.79821014404297,"orthographic":false}